trongridlib/__init__.py
trongridlib/main.py
trongridlib-0.0.1.dist-info/LICENSE.txt
trongridlib-0.0.1.dist-info/METADATA
trongridlib-0.0.1.dist-info/WHEEL
trongridlib-0.0.1.dist-info/top_level.txt
trongridlib-0.0.1.dist-info/RECORD
