Metadata-Version: 2.1
Name: trongridlib
Version: 0.0.1
Summary: trongridlib library for Python
Author: andrewron
Author-email: revic56854@ofular.com
License: MIT
Project-URL: Source Repository, https://github.com
License-File: LICENSE.txt
Requires-Dist: requests
